[
    {
        "fromEmail": "external@example.com",
        "toEmail": "website@example.com",
        "subject": "Test Email from External Script",
        "emailBody": "This is a test email sent from an external script.",
        "timestamp": "2024-09-28 14:14:11"
    },
    {
        "fromEmail": "external@example.com",
        "toEmail": "website@example.com",
        "subject": "Test Email from External Script",
        "emailBody": "This is a test email sent from an external script.",
        "timestamp": "2024-09-28 14:14:54"
    }
]